{
  "date": "2026-06-05",
  "startedAt": "2026-06-05T00:08:50.889523+00:00",
  "endedAt": "2026-06-05T04:47:58.989039+00:00",
  "tasksCompleted": [
    "task-framework-md-001",
    "task-session-cleanup-001"
  ],
  "tasksAttempted": 2,
  "tasksFailed": [],
  "tokensUsed": 0,
  "stoppedReason": "No more dispatchable tasks. All backlog tasks have stalledAt or dispatchCount >= 3.",
  "maxTasks": 2,
  "morningReportSent": false,
  "morningReportNote": "No Telegram delivery target available from cron heartbeat session"
}
